teamindexscore/__init__.py
teamindexscore/core.py
teamindexscore-0.2.0.dist-info/licenses/LICENSE
teamindexscore-0.2.0.dist-info/METADATA
teamindexscore-0.2.0.dist-info/WHEEL
teamindexscore-0.2.0.dist-info/top_level.txt
teamindexscore-0.2.0.dist-info/RECORD
