Metadata-Version: 2.4
Name: TeamIndexScore
Version: 0.2.0
Summary: A professional Python package for calculating an explainable performance index (0-100) for football teams based on league statistics
Author-email: Alvaro Lopez Molina <alopezmolina4@gmail.com>
License-Expression: MIT
Project-URL: Homepage, https://github.com/alvarolopezmolina/TeamIndexScore
Project-URL: Repository, https://github.com/alvarolopezmolina/TeamIndexScore
Project-URL: Documentation, https://github.com/alvarolopezmolina/TeamIndexScore#readme
Keywords: football,soccer,analytics,performance,index,sports
Classifier: Development Status :: 3 - Alpha
Classifier: Intended Audience :: Developers
Classifier: Intended Audience :: Science/Research
Classifier: Programming Language :: Python :: 3
Classifier: Programming Language :: Python :: 3.9
Classifier: Programming Language :: Python :: 3.10
Classifier: Programming Language :: Python :: 3.11
Classifier: Programming Language :: Python :: 3.12
Classifier: Topic :: Scientific/Engineering
Classifier: Topic :: Software Development :: Libraries :: Python Modules
Requires-Python: >=3.9
License-File: LICENSE
Dynamic: license-file
